cinful/Snakefile
cinful/__init__.py
cinful/cinful.py
cinful/cinful_initialize.py
cinful/config.yaml
cinful/input/CvaB.verified.pep
cinful/input/MFP.verified.pep
cinful/input/SP.verified.pep
cinful/input/immunity_proteins.verified.pep
cinful/input/microcins.verified.pep
cinful/rules/CvaB.smk
cinful/rules/MFP.smk
cinful/rules/best_hits.smk
cinful/rules/duomolog_components.smk
cinful/rules/filter_input.smk
cinful/rules/immunity_protein.smk
cinful/rules/microcin.smk
cinful/rules/prodigal.smk
cinful/rules/setup_dbs.smk
cinful-1.2.6.dist-info/LICENSE
cinful-1.2.6.dist-info/METADATA
cinful-1.2.6.dist-info/WHEEL
cinful-1.2.6.dist-info/entry_points.txt
cinful-1.2.6.dist-info/top_level.txt
cinful-1.2.6.dist-info/RECORD
