Metadata-Version: 2.1
Name: cinful
Version: 1.2.6
Summary: cinful: A fully automated pipeline to identify microcinswith associated immunity proteins and export machinery
Home-page: https://github.com/wilkelab/cinful
Author: Aaron Feller
Author-email: aaronleefeller@gmail.com
License: GPL-3
License-File: LICENSE
